src/__init__.py
src/deadlinkz.py
tests/__init__.py
tests/test_openfile.py
tests/test_urls.py
deadlinkz-1.0.3.dist-info/LICENSE
deadlinkz-1.0.3.dist-info/METADATA
deadlinkz-1.0.3.dist-info/WHEEL
deadlinkz-1.0.3.dist-info/entry_points.txt
deadlinkz-1.0.3.dist-info/top_level.txt
deadlinkz-1.0.3.dist-info/RECORD
