Metadata-Version: 2.1
Name: deadlinkz
Version: 1.0.3
Summary: Program that checks for dead links in a file
Home-page: https://github.com/IcemanEtika/deadlinkz
Author: TJ L
Author-email: ssjarceus@outlook.com
License: UNKNOWN
Platform: UNKNOWN
Classifier: Programming Language :: Python :: 3
Classifier: License :: OSI Approved :: MIT License
Classifier: Operating System :: OS Independent
Requires-Python: >=3.7
Requires-Dist: requests (==2.24.0)
Requires-Dist: colorama (==0.4.4)
Requires-Dist: black (==20.8b1)
Requires-Dist: flake8 (==3.8.4)
Requires-Dist: pytest (==6.1.2)
Requires-Dist: coverage (==5.3.0)
